anova_oven_sdk/__init__.py
anova_oven_sdk/client.py
anova_oven_sdk/commands.py
anova_oven_sdk/exceptions.py
anova_oven_sdk/logging_config.py
anova_oven_sdk/models.py
anova_oven_sdk/oven.py
anova_oven_sdk/presets.py
anova_oven_sdk/settings.py
anova_oven_sdk/utils.py
anova_precision_oven_sdk-2025.11.0.dist-info/licenses/LICENSE
anova_precision_oven_sdk-2025.11.0.dist-info/METADATA
anova_precision_oven_sdk-2025.11.0.dist-info/WHEEL
anova_precision_oven_sdk-2025.11.0.dist-info/top_level.txt
anova_precision_oven_sdk-2025.11.0.dist-info/RECORD
