Metadata-Version: 2.4
Name: anova-precision-oven-sdk
Version: 2025.11.0
Summary: Python SDK for Anova Precision Oven
Author-email: Paul Stark <cakes-weighty.9z@icloud.com>
Maintainer-email: Paul Stark <cakes-weighty.9z@icloud.com>
License-Expression: GPL-3.0-or-later
Project-URL: homepage, https://github.com/agentcipher/anova-precision-oven
Project-URL: repository, https://github.com/agentcipher/anova-precision-oven
Keywords: anova,oven,smart-kitchen,home-automation
Classifier: Development Status :: 4 - Beta
Classifier: Intended Audience :: Developers
Classifier: Programming Language :: Python :: 3
Classifier: Programming Language :: Python :: 3.9
Classifier: Programming Language :: Python :: 3.10
Classifier: Programming Language :: Python :: 3.11
Classifier: Programming Language :: Python :: 3.12
Classifier: Programming Language :: Python :: 3.13
Requires-Python: >=3.9
License-File: LICENSE
Requires-Dist: dynaconf
Requires-Dist: pydantic
Requires-Dist: websockets
Provides-Extra: dev
Requires-Dist: pytest>=7.4.0; extra == "dev"
Requires-Dist: pytest-asyncio>=0.21.0; extra == "dev"
Requires-Dist: pytest-cov>=4.1.0; extra == "dev"
Requires-Dist: pytest-mock>=3.11.0; extra == "dev"
Requires-Dist: pytest-xdist>=3.3.0; extra == "dev"
Requires-Dist: black>=23.0.0; extra == "dev"
Requires-Dist: ruff>=0.1.0; extra == "dev"
Requires-Dist: mypy>=1.5.0; extra == "dev"
Dynamic: license-file
